twclient/__init__.py
twclient/_job_base.py
twclient/_job_config.py
twclient/_job_export.py
twclient/_job_fetch.py
twclient/_job_initialize.py
twclient/_job_show.py
twclient/_job_tag.py
twclient/_utils.py
twclient/_version.py
twclient/authpool.py
twclient/config.py
twclient/error.py
twclient/job.py
twclient/models.py
twclient/target.py
twclient/twitter_api.py
twclient/_cli/__init__.py
twclient/_cli/command.py
twclient/_cli/config.py
twclient/_cli/entrypoint.py
twclient/_cli/export.py
twclient/_cli/fetch.py
twclient/_cli/initialize.py
twclient/_cli/show.py
twclient/_cli/tag.py
twclient-0.2.0.dist-info/LICENSE.rst
twclient-0.2.0.dist-info/METADATA
twclient-0.2.0.dist-info/WHEEL
twclient-0.2.0.dist-info/entry_points.txt
twclient-0.2.0.dist-info/top_level.txt
twclient-0.2.0.dist-info/zip-safe
twclient-0.2.0.dist-info/RECORD
