Metadata-Version: 2.1
Name: twclient
Version: 0.2.0
Summary: A high-level analytics-focused client for the Twitter API
Home-page: https://github.com/social-machines/twclient
Author: William Brannon
Author-email: wbrannon@mit.edu
License: Apache 2.0
Project-URL: Source Code, https://github.com/mit-ccc/twclient
Project-URL: Bug Tracker, https://github.com/mit-ccc/twclient/issues
Project-URL: Changelog, https://github.com/mit-ccc/twclient/blob/main/CHANGELOG.md
Project-URL: Documentation, https://mit-ccc.github.io/twclient
Keywords: twitter,tweepy,data science,analytics
Platform: any
Classifier: Development Status :: 4 - Beta
Classifier: License :: OSI Approved :: Apache Software License
Classifier: Operating System :: OS Independent
Classifier: Programming Language :: Python
Classifier: Programming Language :: Python :: 3
Classifier: Topic :: Software Development :: Libraries :: Python Modules
Requires-Python: >=3.7
License-File: LICENSE.rst
Requires-Dist: tweepy
Requires-Dist: sqlalchemy
Requires-Dist: packaging
Provides-Extra: check
Requires-Dist: tox (>=4.0.0) ; extra == 'check'
Requires-Dist: pytest ; extra == 'check'
Requires-Dist: vcrpy ; extra == 'check'
Requires-Dist: pytest-recording ; extra == 'check'
Requires-Dist: coverage ; extra == 'check'
Requires-Dist: mypy ; extra == 'check'
Requires-Dist: pylint ; extra == 'check'
Provides-Extra: ci
Requires-Dist: tox (>=4.0.0) ; extra == 'ci'
Requires-Dist: pytest ; extra == 'ci'
Requires-Dist: vcrpy ; extra == 'ci'
Requires-Dist: pytest-recording ; extra == 'ci'
Requires-Dist: coverage ; extra == 'ci'
Requires-Dist: mypy ; extra == 'ci'
Requires-Dist: pylint ; extra == 'ci'
Requires-Dist: codecov ; extra == 'ci'
Requires-Dist: tox-gh-actions ; extra == 'ci'
Provides-Extra: dev
Requires-Dist: tox (>=4.0.0) ; extra == 'dev'
Requires-Dist: pytest ; extra == 'dev'
Requires-Dist: vcrpy ; extra == 'dev'
Requires-Dist: pytest-recording ; extra == 'dev'
Requires-Dist: coverage ; extra == 'dev'
Requires-Dist: mypy ; extra == 'dev'
Requires-Dist: pylint ; extra == 'dev'
Requires-Dist: sphinx (>=4.3.0) ; extra == 'dev'
Requires-Dist: sphinx-rtd-theme (>=1.2.0rc2) ; extra == 'dev'
Requires-Dist: recommonmark ; extra == 'dev'
Requires-Dist: psycopg2 ; extra == 'dev'
Requires-Dist: mysql-connector-python ; extra == 'dev'
Provides-Extra: docs
Requires-Dist: sphinx (>=4.3.0) ; extra == 'docs'
Requires-Dist: sphinx-rtd-theme (>=1.2.0rc2) ; extra == 'docs'
Requires-Dist: recommonmark ; extra == 'docs'
Provides-Extra: lint
Requires-Dist: mypy ; extra == 'lint'
Requires-Dist: pylint ; extra == 'lint'
Provides-Extra: test
Requires-Dist: tox (>=4.0.0) ; extra == 'test'
Requires-Dist: pytest ; extra == 'test'
Requires-Dist: vcrpy ; extra == 'test'
Requires-Dist: pytest-recording ; extra == 'test'
Requires-Dist: coverage ; extra == 'test'
